bgm_toolkit_pro/__init__.py
bgm_toolkit_pro/cli.py
bgm_toolkit_pro-0.2.19.dist-info/METADATA
bgm_toolkit_pro-0.2.19.dist-info/WHEEL
bgm_toolkit_pro-0.2.19.dist-info/entry_points.txt
bgm_toolkit_pro-0.2.19.dist-info/top_level.txt
bgm_toolkit_pro-0.2.19.dist-info/RECORD
