Metadata-Version: 2.4
Name: bgm-toolkit-pro
Version: 0.2.19
Summary: Bourdieu-inspired gravity model toolkit (Pro core)
Author: Arturo Rubalcava
Requires-Python: >=3.9
Requires-Dist: numpy>=1.24
Requires-Dist: pandas>=2.0
Requires-Dist: statsmodels>=0.14
Requires-Dist: openpyxl>=3.1
Requires-Dist: PyYAML>=6.0
Requires-Dist: jinja2>=3.1
